{
    "Distance": [
        {
            "contactDamage": 1,
            "health": 10,
            "lifeTimeBoost": 2,
            "maxHealth": 10,
            "origin": [
                0.5,
                0.8999999761581421
            ],
            "range": 10,
            "reloadTime": 1.5,
            "size": [
                1,
                1
            ],
            "spellDamage": 1,
            "sprite": "distance",
            "startPos": [
                -50.709999084472656,
                -19.469999313354492
            ]
        }
    ],
    "FlyInfo": [
        {
            "damage": 1,
            "divingSpeed": 10,
            "maxHealth": 2,
            "minDistance": 3,
            "radius": 0.5,
            "speed": 4,
            "startPos": [
                -70.02999877929688,
                -17.369998931884766
            ],
            "timeToDecide": 1,
            "timeToDive": {
                "kind": 0,
                "mean": 10,
                "min": 0,
                "range": 2
            }
        }
    ],
    "MeleeGuyInfo": [
        {
            "attackOrigin": [
                0,
                -0.4000000059604645
            ],
            "attackPersistence": 0.699999988079071,
            "attackRadius": 0.5,
            "attackRange": 1.5,
            "cd": 2,
            "damage": 1,
            "health": 5,
            "origin": [
                0.5,
                0.8999999761581421
            ],
            "size": [
                0.699999988079071,
                1.2000000476837158
            ],
            "speed": 5,
            "startPos": [
                -74.72000122070312,
                -17.279998779296875
            ],
            "viewRange": 5
        }
    ],
    "NavigationLinkInfo": [
        {
            "A": 407,
            "B": 408,
            "id": 413
        },
        {
            "A": 419,
            "B": 418,
            "id": 423
        },
        {
            "A": 424,
            "B": 425,
            "id": 434
        },
        {
            "A": 428,
            "B": 430,
            "id": 438
        },
        {
            "A": 427,
            "B": 426,
            "id": 442
        }
    ],
    "NavigationPointInfo": [
        {
            "id": 407,
            "links": [
                413
            ],
            "pos": [
                -59.52000045776367,
                -19.19999885559082
            ],
            "range": 0.30000001192092896
        },
        {
            "id": 408,
            "links": [
                413
            ],
            "pos": [
                -55.439998626708984,
                -19.279998779296875
            ],
            "range": 0.30000001192092896
        },
        {
            "id": 418,
            "links": [
                423
            ],
            "pos": [
                -59.279998779296875,
                -19.19999885559082
            ],
            "range": 0.30000001192092896
        },
        {
            "id": 419,
            "links": [
                423
            ],
            "pos": [
                -50.07999801635742,
                -19.19999885559082
            ],
            "range": 0.30000001192092896
        },
        {
            "id": 424,
            "links": [
                434
            ],
            "pos": [
                -75.19999694824219,
                -16.479999542236328
            ],
            "range": 0.30000001192092896
        },
        {
            "id": 425,
            "links": [
                434
            ],
            "pos": [
                -69.36000061035156,
                -16.399999618530273
            ],
            "range": 0.30000001192092896
        },
        {
            "id": 426,
            "links": [
                442
            ],
            "pos": [
                -79.5999984741211,
                -13.359999656677246
            ],
            "range": 0.30000001192092896
        },
        {
            "id": 427,
            "links": [
                442
            ],
            "pos": [
                -55.84000015258789,
                -13.199999809265137
            ],
            "range": 0.30000001192092896
        },
        {
            "id": 428,
            "links": [
                438
            ],
            "pos": [
                -55.279998779296875,
                -20.479999542236328
            ],
            "range": 0.30000001192092896
        },
        {
            "id": 430,
            "links": [
                438
            ],
            "pos": [
                -50,
                -20.479999542236328
            ],
            "range": 0.30000001192092896
        }
    ],
    "PlateformeInfo": [
        {
            "rectangle": [
                -79.91999816894531,
                -12.960000038146973,
                16.31999969482422,
                0.32000064849853516
            ]
        },
        {
            "rectangle": [
                -79.91999816894531,
                -16.239999771118164,
                4,
                0.31999969482421875
            ]
        },
        {
            "rectangle": [
                -75.91999816894531,
                -21.119998931884766,
                0.31999969482421875,
                5.19999885559082
            ]
        },
        {
            "rectangle": [
                -78.4000015258789,
                -21.119998931884766,
                2.8000030517578125,
                0.31999969482421875
            ]
        },
        {
            "rectangle": [
                -78.72000122070312,
                -24.559999465942383,
                0.31999969482421875,
                3.760000228881836
            ]
        },
        {
            "rectangle": [
                -78.63999938964844,
                -24.559999465942383,
                18.15999984741211,
                0.39999961853027344
            ]
        },
        {
            "rectangle": [
                -76.15999603271484,
                -16.239999771118164,
                7.040000915527344,
                0.31999969482421875
            ]
        },
        {
            "rectangle": [
                -63.68000030517578,
                -12.960000038146973,
                8.480003356933594,
                0.32000064849853516
            ]
        },
        {
            "rectangle": [
                -55.52000045776367,
                -20.31999969482422,
                5.680000305175781,
                0.31999969482421875
            ]
        },
        {
            "rectangle": [
                -61.19999694824219,
                -24.559999465942383,
                11.279998779296875,
                0.39999961853027344
            ]
        },
        {
            "rectangle": [
                -59.68000030517578,
                -18.8799991607666,
                4.159999847412109,
                0.31999969482421875
            ]
        },
        {
            "rectangle": [
                -55.52000045776367,
                -18.8799991607666,
                0.3200035095214844,
                6.159999847412109
            ]
        },
        {
            "rectangle": [
                -55.52000045776367,
                -18.8799991607666,
                5.680000305175781,
                0.23999977111816406
            ]
        },
        {
            "rectangle": [
                -50,
                -20.31999969482422,
                0.40000152587890625,
                1.6800003051757812
            ]
        },
        {
            "rectangle": [
                -50,
                -24.559999465942383,
                2.799999237060547,
                0.39999961853027344
            ]
        },
        {
            "rectangle": [
                -50,
                -20.399999618530273,
                3.1200027465820312,
                0.31999969482421875
            ]
        },
        {
            "rectangle": [
                -47.279998779296875,
                -24.559999465942383,
                0.40000152587890625,
                4.159999847412109
            ]
        },
        {
            "rectangle": [
                -80.15999603271484,
                -16.239999771118164,
                0.31999969482421875,
                3.6000003814697266
            ]
        }
    ],
    "Slime": [
        {
            "contactDamage": 1,
            "health": 10,
            "maxHealth": 10,
            "size": [
                1,
                0.6000000238418579
            ],
            "speed": 5,
            "sprite": "slime",
            "startPos": [
                -56.12999725341797,
                -19.529998779296875
            ],
            "viewRange": 7
        }
    ],
    "SourceDirectionInfo": [
        {
            "id": 0,
            "kind": 10285511,
            "origin": [
                0.5,
                0.8999999761581421
            ],
            "pos": [
                -77.2699966430664,
                -21.5
            ],
            "range": 0.800000011920929,
            "reloadTime": 0.10000000149011612,
            "size": [
                0.6600000262260437,
                0.6600000262260437
            ],
            "sprite": "SourceDirection"
        }
    ],
    "SourceTargetInfo": [],
    "SourceVaccumInfo": [
        {
            "id": 0,
            "kind": 10285511,
            "origin": [
                0.5,
                0.8999999761581421
            ],
            "pos": [
                -49.59000015258789,
                -20.079999923706055
            ],
            "range": 0.5,
            "reloadTime": 0,
            "size": [
                0.6600000262260437,
                0.6600000262260437
            ],
            "sprite": "SourceVaccum"
        },
        {
            "id": 0,
            "kind": 10285511,
            "origin": [
                0.5,
                0.8999999761581421
            ],
            "pos": [
                -50.80999755859375,
                -20.90999984741211
            ],
            "range": 0.5,
            "reloadTime": 0,
            "size": [
                0.6600000262260437,
                0.6600000262260437
            ],
            "sprite": "SourceVaccum"
        }
    ],
    "maxRect": [
        -82.3499984741211,
        -27.68000030517578,
        35.470001220703125,
        15.040000915527344
    ],
    "source": [],
    "startPos": [
        -78.5,
        -14.579999923706055
    ],
    "viewSize": [
        19.440040588378906,
        12.150028228759766
    ]
}