{"Distance":[],"FirstBossInfo":[],"FlyInfo":[],"MeleeGuyInfo":[],"NavigationLinkInfo":[],"NavigationPointInfo":[],"PlateformeInfo":[{"passable":false,"rectangle":[-212.75,-116.5,0.25,2.75]},{"passable":true,"rectangle":[-212.75,-114.0,2.5,0.25]},{"passable":false,"rectangle":[-210.25,-116.5,0.25,2.75]},{"passable":false,"rectangle":[-212.5,-116.5,2.25,0.25]},{"passable":false,"rectangle":[-210.25,-113.75,0.25,5.0]},{"passable":false,"rectangle":[-217.25,-108.75,7.25,0.25]},{"passable":false,"rectangle":[-217.25,-108.5,0.25,4.5]},{"passable":false,"rectangle":[-229.5,-104.25,12.25,0.25]},{"passable":false,"rectangle":[-236.0,-116.0,23.25,0.25]},{"passable":true,"rectangle":[-219.5,-110.0,0.75,0.25]},{"passable":false,"rectangle":[-236.0,-112.75,6.25,0.25]},{"passable":false,"rectangle":[-229.75,-112.75,0.25,8.75]},{"passable":false,"rectangle":[-236.0,-115.75,0.25,3.0]},{"passable":true,"rectangle":[-223.5,-111.0,0.75,0.25]},{"passable":true,"rectangle":[-226.75,-111.5,0.75,0.25]}],"PortalInfo":[],"SemiPlateformeInfo":[],"Slime":[],"SourceDirectionInfo":[],"SourceTargetInfo":[],"SourceVaccumInfo":[],"maxRect":[-236.0,-116.5,26.0,12.5],"source":[],"startPos":[-233.8300018310547,-113.55999755859375],"viewSize":[16.20003318786621,10.125022888183594]}